maleo/cds/__init__.py
maleo/cds/db.py
maleo/cds/client/__init__.py
maleo/cds/constants/__init__.py
maleo/cds/constants/coding/__init__.py
maleo/cds/constants/coding/diagnosis.py
maleo/cds/constants/coding/procedure.py
maleo/cds/constants/coding/record.py
maleo/cds/dtos/__init__.py
maleo/cds/dtos/configuration.py
maleo/cds/dtos/settings.py
maleo/cds/dtos/coding/__init__.py
maleo/cds/dtos/coding/diagnosis.py
maleo/cds/dtos/coding/procedure.py
maleo/cds/dtos/coding/record.py
maleo/cds/enums/__init__.py
maleo/cds/enums/general.py
maleo/cds/enums/coding/__init__.py
maleo/cds/enums/coding/diagnosis.py
maleo/cds/enums/coding/procedure.py
maleo/cds/enums/coding/record.py
maleo/cds/mixins/__init__.py
maleo/cds/mixins/general.py
maleo/cds/models/__init__.py
maleo/cds/models/coding/__init__.py
maleo/cds/models/coding/diagnosis.py
maleo/cds/models/coding/procedure.py
maleo/cds/models/coding/record.py
maleo/cds/schemas/__init__.py
maleo/cds/schemas/data/__init__.py
maleo/cds/schemas/data/coding/__init__.py
maleo/cds/schemas/data/coding/diagnosis.py
maleo/cds/schemas/data/coding/procedure.py
maleo/cds/schemas/data/coding/record.py
maleo/cds/schemas/metadata/__init__.py
maleo/cds/schemas/metadata/coding/__init__.py
maleo/cds/schemas/metadata/coding/diagnosis.py
maleo/cds/schemas/metadata/coding/procedure.py
maleo/cds/schemas/parameter/__init__.py
maleo/cds/schemas/parameter/client/__init__.py
maleo/cds/schemas/parameter/client/coding/__init__.py
maleo/cds/schemas/parameter/client/coding/diagnosis.py
maleo/cds/schemas/parameter/client/coding/procedure.py
maleo/cds/schemas/parameter/general/__init__.py
maleo/cds/schemas/parameter/general/coding/__init__.py
maleo/cds/schemas/parameter/general/coding/diagnosis.py
maleo/cds/schemas/parameter/general/coding/procedure.py
maleo/cds/schemas/parameter/general/coding/record.py
maleo/cds/schemas/parameter/service/__init__.py
maleo/cds/schemas/parameter/service/coding/__init__.py
maleo/cds/schemas/parameter/service/coding/diagnosis.py
maleo_cds-0.1.35.dist-info/METADATA
maleo_cds-0.1.35.dist-info/WHEEL
maleo_cds-0.1.35.dist-info/top_level.txt
maleo_cds-0.1.35.dist-info/RECORD
