Metadata-Version: 2.4
Name: maleo-cds
Version: 0.1.35
Summary: MaleoCDS service package
Author-email: Agra Bima Yuda <agra@nexmedis.com>
License: MIT
Requires-Python: >=3.12
Requires-Dist: maleo_soma>=0.1.93
Requires-Dist: maleo_metadata>=0.2.50
